demo/__init__.py
demo/cli.py
demo/manage_secrets.py
demo_python_aws_click-0.0.1.dev4.dist-info/LICENSE
demo_python_aws_click-0.0.1.dev4.dist-info/METADATA
demo_python_aws_click-0.0.1.dev4.dist-info/WHEEL
demo_python_aws_click-0.0.1.dev4.dist-info/entry_points.txt
demo_python_aws_click-0.0.1.dev4.dist-info/top_level.txt
demo_python_aws_click-0.0.1.dev4.dist-info/RECORD
